vasara/__init__.py
vasara/__main__.py
vasara/core.py
vasara-0.2.0.dist-info/LICENCE
vasara-0.2.0.dist-info/METADATA
vasara-0.2.0.dist-info/WHEEL
vasara-0.2.0.dist-info/entry_points.txt
vasara-0.2.0.dist-info/RECORD
