Metadata-Version: 2.3
Name: vasara
Version: 0.2.0
Summary: A fun little command-line tool for fetching random Warhammer lore snippets from the wikis.
License: GPL-3.0-only
Author: It Ankka
Author-email: github@cote.mozmail.com
Requires-Python: >=3.10,<4.0
Classifier: License :: OSI Approved :: GNU General Public License v3 (GPLv3)
Classifier: Programming Language :: Python :: 3
Classifier: Programming Language :: Python :: 3.10
Classifier: Programming Language :: Python :: 3.11
Classifier: Programming Language :: Python :: 3.12
Classifier: Programming Language :: Python :: 3.13
Requires-Dist: requests (>=2.32.5,<3.0.0)
Requires-Dist: wikitextparser (>=0.56.4,<0.57.0)
